cosmpy/__init__.py
cosmpy/aerial/__init__.py
cosmpy/aerial/client/__init__.py
cosmpy/aerial/client/bank.py
cosmpy/aerial/client/distribution.py
cosmpy/aerial/client/staking.py
cosmpy/aerial/client/utils.py
cosmpy/aerial/coins.py
cosmpy/aerial/config.py
cosmpy/aerial/contract/__init__.py
cosmpy/aerial/contract/cosmwasm.py
cosmpy/aerial/exceptions.py
cosmpy/aerial/faucet.py
cosmpy/aerial/gas.py
cosmpy/aerial/tx.py
cosmpy/aerial/tx_helpers.py
cosmpy/aerial/types.py
cosmpy/aerial/urls.py
cosmpy/aerial/wallet.py
cosmpy/auth/__init__.py
cosmpy/auth/interface.py
cosmpy/auth/rest_client.py
cosmpy/bank/__init__.py
cosmpy/bank/interface.py
cosmpy/bank/rest_client.py
cosmpy/common/__init__.py
cosmpy/common/rest_client.py
cosmpy/common/types.py
cosmpy/common/utils.py
cosmpy/cosmwasm/__init__.py
cosmpy/cosmwasm/interface.py
cosmpy/cosmwasm/rest_client.py
cosmpy/crypto/__init__.py
cosmpy/crypto/address.py
cosmpy/crypto/hashfuncs.py
cosmpy/crypto/interface.py
cosmpy/crypto/keypairs.py
cosmpy/distribution/__init__.py
cosmpy/distribution/interface.py
cosmpy/distribution/rest_client.py
cosmpy/evidence/__init__.py
cosmpy/evidence/interface.py
cosmpy/evidence/rest_client.py
cosmpy/gov/__init__.py
cosmpy/gov/interface.py
cosmpy/gov/rest_client.py
cosmpy/ibc/__init__.py
cosmpy/ibc/applications/transfer/__init__.py
cosmpy/ibc/applications/transfer/interface.py
cosmpy/ibc/applications/transfer/rest_client.py
cosmpy/ibc/core/channel/__init__.py
cosmpy/ibc/core/channel/interface.py
cosmpy/ibc/core/channel/rest_client.py
cosmpy/ibc/core/client/__init__.py
cosmpy/ibc/core/client/interface.py
cosmpy/ibc/core/client/rest_client.py
cosmpy/ibc/core/connection/__init__.py
cosmpy/ibc/core/connection/interface.py
cosmpy/ibc/core/connection/rest_client.py
cosmpy/mint/__init__.py
cosmpy/mint/interface.py
cosmpy/mint/rest_client.py
cosmpy/mnemonic/__init__.py
cosmpy/mnemonic/words/__init__.py
cosmpy/mnemonic/words/english.py
cosmpy/params/__init__.py
cosmpy/params/interface.py
cosmpy-0.11.0.dist-info/AUTHORS.md
cosmpy-0.11.0.dist-info/LICENSE
cosmpy-0.11.0.dist-info/METADATA
cosmpy-0.11.0.dist-info/WHEEL
cosmpy-0.11.0.dist-info/RECORD
