Metadata-Version: 2.3
Name: cosmpy
Version: 0.11.0
Summary: A library for interacting with the cosmos networks
License: Apache-2.0
Keywords: CosmPy,Cosmos-SDK
Author: Fetch.AI Limited
Requires-Python: >=3.9,<4.0
Classifier: Development Status :: 3 - Alpha
Classifier: Environment :: Console
Classifier: Intended Audience :: Developers
Classifier: Intended Audience :: Information Technology
Classifier: License :: OSI Approved :: Apache Software License
Classifier: Natural Language :: English
Classifier: Operating System :: MacOS
Classifier: Operating System :: Microsoft :: Windows
Classifier: Operating System :: Unix
Classifier: Programming Language :: Python :: 3
Classifier: Programming Language :: Python :: 3.9
Classifier: Programming Language :: Python :: 3.10
Classifier: Programming Language :: Python :: 3.11
Classifier: Programming Language :: Python :: 3.12
Classifier: Programming Language :: Python :: 3.13
Classifier: Topic :: Software Development
Classifier: Topic :: Software Development :: Libraries :: Python Modules
Classifier: Topic :: System
Requires-Dist: bech32
Requires-Dist: ecdsa
Requires-Dist: googleapis-common-protos
Requires-Dist: grpcio
Requires-Dist: jsonschema (>=3.2.0,<5)
Requires-Dist: protobuf (>=4.21.6,<6.0dev)
Requires-Dist: pycryptodome (>=3.18.0,<4.0.0)
Requires-Dist: python-dateutil
Requires-Dist: requests
Requires-Dist: virtualenv (>=20.26.6)
Project-URL: Documentation, https://network.fetch.ai/docs/guides/cosmpy/installation/
Project-URL: Homepage, https://github.com/fetchai/cosmpy
Project-URL: Repository, https://github.com/fetchai/cosmpy
